[
    {
        "username": "nov.tvgag.er.al@gmail.com",
        "password": "uS9DdzITbQ"
    },
    {
        "username": "nov.tvga.ge.ral@gmail.com",
        "password": "w2tEf2c89N"
    },
    {
        "username": "novt.v.g.a.ge.r.al@gmail.com",
        "password": "4PEG72eZ6M"
    },
    {
        "username": "nov.tvgage.r.al@gmail.com",
        "password": "21UV8Q2KnE"
    },
    {
        "username": "nov.tvga.geral@gmail.com",
        "password": "g90xazx8i9"
    },
    {
        "username": "nov.tvgag.eral@gmail.com",
        "password": "zrDOUKt1Gf"
    },
    {
        "username": "novt.v.g.a.ge.ral@gmail.com",
        "password": "VAXKvAShT3"
    },
    {
        "username": "nov.tvgager.al@gmail.com",
        "password": "9XpI33lGXq"
    },
    {
        "username": "novt.v.g.a.geral@gmail.com",
        "password": "7CjAyRM78W"
    },
    {
        "username": "novt.v.g.a.g.er.al@gmail.com",
        "password": "3GWEyOPHai"
    },
    {
        "username": "nov.tvgag.e.r.al@gmail.com",
        "password": "sCRAMA1OQw"
    },
    {
        "username": "novt.v.g.a.g.e.ral@gmail.com",
        "password": "AQ4ZfFdOzF"
    },
    {
        "username": "novt.v.g.a.g.eral@gmail.com",
        "password": "KnJdMyTEr7"
    },
    {
        "username": "novt.v.g.ag.e.ral@gmail.com",
        "password": "VREZZW5Opu"
    },
    {
        "username": "novt.v.g.a.ger.al@gmail.com",
        "password": "XBqxjgps7F"
    },
    {
        "username": "nov.tvgageral@gmail.com",
        "password": "vXdxT79fNE"
    },
    {
        "username": "novt.v.g.a.g.e.r.al@gmail.com",
        "password": "Br2q8kz1af"
    },
    {
        "username": "novt.v.g.a.ge.ra.l@gmail.com",
        "password": "IbnTNCRdiG"
    },
    {
        "username": "novt.v.g.ag.e.ra.l@gmail.com",
        "password": "wIfQFVNERR"
    },
    {
        "username": "novt.v.g.a.g.era.l@gmail.com",
        "password": "moVdrjsx1l"
    },
    {
        "username": "novt.v.g.a.gera.l@gmail.com",
        "password": "CY3UVa4oSF"
    }
]